{
	"canciones": [
		{
			"nombre": "vive",
			"ruta": "one.mp3",
			"reproducciones": 10,
			"icono": 4
		},
		{
			"nombre": "invierno",
			"ruta": "two.mp3",
			"reproducciones": 30,
			"icono": 1
		},
		{
			"nombre": "planeta",
			"ruta": "three.mp3",
			"reproducciones": 20,
			"icono": 3
		},
		{
			"nombre": "suave",
			"ruta": "four.mp3",
			"reproducciones": 80,
			"icono": 2
		},
		{
			"nombre": "contigo",
			"ruta": "five.mp3",
			"reproducciones": 50,
			"icono": 4
		},
		{
			"nombre": "alas",
			"ruta": "six.mp3",
			"reproducciones": 70,
			"icono": 1
		},
		{
			"nombre": "verde",
			"ruta": "seven.mp3",
			"reproducciones": 60,
			"icono": 3
		},
		{
			"nombre": "nuevamente",
			"ruta": "eight.mp3",
			"reproducciones": 90,
			"icono": 1
		},
		{
			"nombre": "hoy",
			"ruta": "nine.mp3",
			"reproducciones": 40,
			"icono": 2
		}
	]
}
